walt/__init__.py
walt/node/__init__.py
walt/node/const.py
walt/node/ipxekexec.py
walt/node/logs/__init__.py
walt/node/logs/cache.py
walt/node/logs/daemon.py
walt/node/logs/flow.py
walt/node/logs/listener.py
walt/node/logs/monitor.py
walt/node/serial/__init__.py
walt/node/serial/autolog.py
walt/node/setup/__init__.py
walt/node/setup/walt-logs.service
walt_node-10.0.data/scripts/walt-log-monitor
walt_node-10.0.data/scripts/walt-monitor
walt_node-10.0.dist-info/METADATA
walt_node-10.0.dist-info/WHEEL
walt_node-10.0.dist-info/entry_points.txt
walt_node-10.0.dist-info/top_level.txt
walt_node-10.0.dist-info/RECORD
